{"id":"Poem_of_Brutulus","url":"Poem_of_Brutulus","title":"Poem of Brutulus","category":"history","subcategory":"the age of awakening","images":{"main":"","other":[]},"details":[],"body":"<h1>Transcript</h1><p><em>As a mountain waits,</em></p><p><em>Until the deep earth wakes,</em></p><p><em>With wrath and anger,</em></p><p><em>It conjures fire and magma.</em></p><p><br></p><p><em>As a volcano trembles,</em></p><p><em>Unleashing flaming terror,</em></p><p><em>Even the bravest men will fly,</em></p><p><em>But all men will die.</em></p><p><br></p><p><em>And as Brutulus walks,</em></p><p><em>So does the Earth quake,</em></p><p><em>And as Brutulus roars,</em></p><p><em>So do his foes shake.</em></p><p><br></p><p><em>And as Brutulus fights,</em></p><p><em>With hammer and sword,</em></p><p><em>With thunder and lightning,</em></p><p><em>He conquers the world.</em></p>","preface":"<p>The Poem of Brutulus is a short poem written about <a href=\"#/view/Brutulus\">Brutulus</a>.</p>","date_created":"Fri Apr 12 2019 19:03:17 GMT+0100 (British Summer Time)","last_updated":"Fri Apr 12 2019 19:03:26 GMT+0100 (British Summer Time)"}